hoostus/beangulp/hooks/__init__.py
hoostus/beangulp/hooks/pipelines.py
hoostus/beangulp/hooks/predict_posting.py
hoostus_beangulp_hooks-1.0.3.dist-info/METADATA
hoostus_beangulp_hooks-1.0.3.dist-info/WHEEL
hoostus_beangulp_hooks-1.0.3.dist-info/top_level.txt
hoostus_beangulp_hooks-1.0.3.dist-info/RECORD
