Metadata-Version: 2.4
Name: hoostus-beangulp-hooks
Version: 1.0.3
Summary: Hooks for the beangulp importer.
Requires-Python: >=3.12
Requires-Dist: beancount>=3.1.0
Requires-Dist: numpy>=2.2.3
Requires-Dist: scikit-learn>=1.6.1
